muffin_peewee/__init__.py
muffin_peewee/fields.py
muffin_peewee/py.typed
muffin_peewee/types.py
muffin_peewee_aio-1.4.0.dist-info/METADATA
muffin_peewee_aio-1.4.0.dist-info/WHEEL
muffin_peewee_aio-1.4.0.dist-info/RECORD
