Metadata-Version: 2.3
Name: muffin-peewee-aio
Version: 1.4.0
Summary: Peewee-AIO integration for Muffin framework
License: MIT
Keywords: peewee,sql,orm,asyncio,muffin
Author: Kirill Klenov
Author-email: horneds@gmail.com
Requires-Python: >=3.10,<4.0
Classifier: Development Status :: 5 - Production/Stable
Classifier: Framework :: AsyncIO
Classifier: Intended Audience :: Developers
Classifier: License :: OSI Approved :: MIT License
Classifier: Programming Language :: Python
Classifier: Programming Language :: Python :: 3
Classifier: Programming Language :: Python :: 3.10
Classifier: Programming Language :: Python :: 3.11
Classifier: Programming Language :: Python :: 3.12
Classifier: Programming Language :: Python :: 3.13
Provides-Extra: aiomysql
Provides-Extra: aiopg
Provides-Extra: aiosqlite
Provides-Extra: asyncpg
Requires-Dist: aiomysql ; extra == "aiomysql"
Requires-Dist: aiopg ; extra == "aiopg"
Requires-Dist: aiosqlite ; extra == "aiosqlite"
Requires-Dist: asyncpg ; extra == "asyncpg"
Requires-Dist: muffin
Requires-Dist: peewee (>=3,<4)
Requires-Dist: peewee-aio
Requires-Dist: peewee-migrate (>=1,<2)
Requires-Dist: typing-extensions ; python_version < "3.11"
Project-URL: Homepage, https://github.com/klen/muffin-peewee
Project-URL: Repository, https://github.com/klen/muffin-peewee
